Digital System Design Lab/Week 3/lab3q4.v
	// Expression = A'D + C'D
	
module lab3q4(a, b, c, d, f, f2);
    input a, b, c, d;
    output f, f2;

    assign f = ~(~(~a & d)) | ~(~(~c & d));

    nor(g1, d);
    nor(g2, ~c, ~a);
    nor(f2, g1, g2);
endmodule

Digital System Design Lab/Week 3/lab3q4_tb.v
`timescale 1ns/1ns
`include "lab3q4.v"

module lab3q4_tb();
reg a,b,c,d;
wire f,f2;
lab3q4 uut(a,b,c,d,f,f2);
initial begin

	$dumpfile("lab3q4_tb.vcd");
	$dumpvars(0, lab3q4_tb);
	a=0;b=0;c=0;d=0;
	#20;
	a=0;b=0;c=0;d=1;
	#20;
	a=0;b=0;c=1;d=0;
	#20;
	a=0;b=0;c=1;d=1;
	#20;
	a=0;b=1;c=0;d=0;
	#20;
	a=0;b=1;c=0;d=1;
	#20;
	a=0;b=1;c=1;d=0;
	#20;
	a=0;b=1;c=1;d=1;
	#20;
	a=1;b=0;c=0;d=0;
	#20;
	a=1;b=0;c=0;d=1;
	#20;
	a=1;b=0;c=1;d=0;
	#20;
	a=1;b=0;c=1;d=1;
	#20;
	a=1;b=1;c=0;d=0;
	#20;
	a=1;b=1;c=0;d=1;
	#20;
	a=1;b=1;c=1;d=0;
	#20;
	a=1;b=1;c=1;d=1;
	#20;
	$display("Test Complete");
end
endmodule

Digital System Design Lab/Week 3/lab3q4_tb.vcd
$date
	Mon Sep  5 10:22:58 2022
$end
$version
	Icarus Verilog
$end
$timescale
	1ns
$end
$scope module lab3q4_tb $end
$var wire 1 ! f2 $end
$var wire 1 " f $end
$var reg 1 # a $end
$var reg 1 $ b $end
$var reg 1 % c $end
$var reg 1 & d $end
$scope module uut $end
$var wire 1 # a $end
$var wire 1 $ b $end
$var wire 1 % c $end
$var wire 1 & d $end
$var wire 1 " f $end
$var wire 1 ! f2 $end
$var wire 1 ' g1 $end
$var wire 1 ( g2 $end
$upscope $end
$upscope $end
$enddefinitions $end
#0
$dumpvars
0(
1'
0&
0%
0$
0#
0"
0!
$end
#20
1"
1!
0'
1&
#40
0"
0!
1'
0&
1%
#60
1"
1!
0'
1&
#80
0"
0!
1'
0&
0%
1$
#100
1"
1!
0'
1&
#120
0"
0!
1'
0&
1%
#140
1"
1!
0'
1&
#160
0"
0!
1'
0&
0%
0$
1#
#180
1"
1!
0'
1&
#200
0"
0!
1(
1'
0&
1%
#220
0'
1&
#240
0(
1'
0&
0%
1$
#260
1"
1!
0'
1&
#280
0"
0!
1(
1'
0&
1%
#300
0'
1&
