Digital System Design Lab/Week 3/lab3q1.v
module lab3q1(a, b, c, d, f, f2);
    input a, b, c, d;
    output f,f2;
    
	//Behavioural Code
	assign f = ~(~(~a&~c))|~(~(~a&d))|~(~(b&~c))|~(~(b&d));

	//Structural Code
    nand(k1, ~a, ~c);
    nand(k2, ~a, d);
    nand(k3, b, ~c);
    nand(k4, b, d);
    nand(f2, k1, k2, k3, k4);

endmodule

Digital System Design Lab/Week 3/lab3q1_tb.v
`timescale 1ns/1ns
`include "lab3q1.v"

module lab3q1_tb;
reg a,b,c,d;
wire f,f2;
lab3q1 uut(a,b,c,d,f,f2);
initial begin

	$dumpfile("lab3q1_tb.vcd");
	$dumpvars(0, lab3q1_tb);
	a=0;b=0;c=0;d=0;
	#20;
	a=0;b=0;c=0;d=1;
	#20;
	a=0;b=0;c=1;d=0;
	#20;
	a=0;b=0;c=1;d=1;
	#20;
	a=0;b=1;c=0;d=0;
	#20;
	a=0;b=1;c=0;d=1;
	#20;
	a=0;b=1;c=1;d=0;
	#20;
	a=0;b=1;c=1;d=1;
	#20;
	a=1;b=0;c=0;d=0;
	#20;
	a=1;b=0;c=0;d=1;
	#20;
	a=1;b=0;c=1;d=0;
	#20;
	a=1;b=0;c=1;d=1;
	#20;
	a=1;b=1;c=0;d=0;
	#20;
	a=1;b=1;c=0;d=1;
	#20;
	a=1;b=1;c=1;d=0;
	#20;
	a=1;b=1;c=1;d=1;
	#20;
	$display("Test Complete");
end
endmodule

Digital System Design Lab/Week 3/lab3q1_tb.vcd
$date
	Mon Sep  5 11:11:51 2022
$end
$version
	Icarus Verilog
$end
$timescale
	1ns
$end
$scope module lab3q1_tb $end
$var wire 1 ! f2 $end
$var wire 1 " f $end
$var reg 1 # a $end
$var reg 1 $ b $end
$var reg 1 % c $end
$var reg 1 & d $end
$scope module uut $end
$var wire 1 # a $end
$var wire 1 $ b $end
$var wire 1 % c $end
$var wire 1 & d $end
$var wire 1 " f $end
$var wire 1 ! f2 $end
$var wire 1 ' k1 $end
$var wire 1 ( k2 $end
$var wire 1 ) k3 $end
$var wire 1 * k4 $end
$upscope $end
$upscope $end
$enddefinitions $end
#0
$dumpvars
1*
1)
1(
0'
0&
0%
0$
0#
1"
1!
$end
#20
0(
1&
#40
0"
0!
1'
1(
0&
1%
#60
1"
1!
0(
1&
#80
0'
0)
1(
0&
0%
1$
#100
0(
0*
1&
#120
0"
0!
1'
1)
1(
1*
0&
1%
#140
1"
1!
0(
0*
1&
#160
0"
0!
1(
1*
0&
0%
0$
1#
#180
1&
#200
0&
1%
#220
1&
#240
1"
1!
0)
0&
0%
1$
#260
0*
1&
#280
0"
0!
1)
1*
0&
1%
#300
1"
1!
0*
1&
