Digital System Design Lab/Week 8/dec3to8.v
module dec3to8(w ,en, f);
    input [2:0] w;
    input en;
    output [7:0] f;
    dec2to4 stage0 (w[1:0], (~w[2] & en), f[3:0]);
    dec2to4 stage1 (w[1:0], (w[2] & en), f[7:4]);

endmodule

module dec2to4(w, en, f);
    input [1:0] w;
    input en; 
    output [3:0] f;
    reg [3:0] f;
    always @ (w or en)
    begin
    if (en == 1)
    begin
    if (w == 2'b00)
        f = 4'b0001;
    if (w == 2'b01)
        f = 4'b0010;
    if (w == 2'b10)
        f = 4'b0100;
    else 
        f = 4'b1000;
    end
    end

endmodule

Digital System Design Lab/Week 8/dec3to8_tb.v
`timescale 1ns/1ns
`include "dec3to8.v"

module dec3to8_tb();
reg [2:0] w;
reg en;
wire [7:0] f;

dec3to8 dec(w,en,f);
initial
begin 

    $dumpfile("dec3to8_tb.vcd");
    $dumpvars(0, dec3to8_tb);

    en = 1; w = 3'b000; #20;
    en = 1; w = 3'b001; #20;
    en = 1; w = 3'b010; #20;
    en = 1; w = 3'b011; #20;
    en = 1; w = 3'b100; #20;
    en = 1; w = 3'b101; #20;
    en = 1; w = 3'b110; #20;
    en = 1; w = 3'b111; #20;

    $display("Test Complete");

end
endmodule

Digital System Design Lab/Week 8/dec3to8_tb.vcd
$date
	Mon Oct 17 11:18:07 2022
$end
$version
	Icarus Verilog
$end
$timescale
	1ns
$end
$scope module dec3to8_tb $end
$var wire 8 ! f [7:0] $end
$var reg 1 " en $end
$var reg 3 # w [2:0] $end
$scope module dec $end
$var wire 1 " en $end
$var wire 3 $ w [2:0] $end
$var wire 8 % f [7:0] $end
$scope module stage0 $end
$var wire 1 & en $end
$var wire 2 ' w [1:0] $end
$var reg 4 ( f [3:0] $end
$upscope $end
$scope module stage1 $end
$var wire 1 ) en $end
$var wire 2 * w [1:0] $end
$var reg 4 + f [3:0] $end
$upscope $end
$upscope $end
$upscope $end
$enddefinitions $end
#0
$dumpvars
bx +
b0 *
0)
b1000 (
b0 '
1&
bx1000 %
b0 $
b0 #
1"
bx1000 !
$end
#20
bx1000 !
bx1000 %
b1000 (
b1 '
b1 *
b1 #
b1 $
#40
bx0100 !
bx0100 %
b100 (
b10 '
b10 *
b10 #
b10 $
#60
bx1000 !
bx1000 %
b1000 (
b11 '
b11 *
b11 #
b11 $
#80
0&
b1000 (
b10001000 !
b10001000 %
b1000 +
1)
b0 '
b0 *
b100 #
b100 $
#100
b10001000 !
b10001000 %
b1000 +
b1 '
b1 *
b101 #
b101 $
#120
b1001000 !
b1001000 %
b100 +
b10 '
b10 *
b110 #
b110 $
#140
b10001000 !
b10001000 %
b1000 +
b11 '
b11 *
b111 #
b111 $
