Digital System Design Lab/Week 1/labex1.v
module labex1(a,b,c,d,f);
input a,b,c,d;
output f;
and(k1,a,b);
and(k2,a,b);
or(k3,k1,c);
or(k4,c,k2);
and(k5,~k3,d);
or(k6,d,k4);
and(f,k5,k6);
endmodule

Digital System Design Lab/Week 1/210905014/Week 1/labex1_input.v
`timescale 1ns/1ns
`include "labex1.v"

module labex1_input();
reg a,b,c,d;
wire f;

labex1 uut(a,b,c,d,f); 
initial begin

	$dumpfile("labex1_input.vcd");
	$dumpvars(0, labex1_input);

	a=0;
	b=0;
	c=0;
	d=0;
	#20;
	
	a=0;
	b=0;
	c=0;
	d=1;
	#20;
	
	a=0;
	b=0;
	c=1;
	d=0;
	#20;
	
	a=0;
	b=0;
	c=1;
	d=1;
	#20;
	
	a=0;
	b=1;
	c=0;
	d=0;
	#20;
	
	a=0;
	b=1;
	c=0;
	d=1;
	#20;
	
	a=0;
	b=1;
	c=1;
	d=0;
	#20;
	
	a=0;
	b=1;
	c=1;
	d=1;
	#20;
	
	a=1;
	b=0;
	c=0;
	d=0;
	#20;
	
	a=1;
	b=0;
	c=0;
	d=1;
	#20;
	
	a=1;
	b=0;
	c=1;
	d=0;
	#20;
	
	a=1;
	b=0;
	c=1;
	d=1;
	#20;
	
	a=1;
	b=1;
	c=0;
	d=0;
	#20;
	
	a=1;
	b=1;
	c=0;
	d=1;
	#20;
	
	a=1;
	b=1;
	c=1;
	d=0;
	#20;	
	
	a=1;
	b=1;
	c=1;
	d=1;
	#20;	
	$display("Test complete");
	
end
endmodule

Digital System Design Lab/Week 1/Lab 1/labex1_input.vcd
$date
	Sun Sep 18 20:01:24 2022
$end
$version
	Icarus Verilog
$end
$timescale
	1ns
$end
$scope module labex1_input $end
$var wire 1 ! f $end
$var reg 1 " a $end
$var reg 1 # b $end
$var reg 1 $ c $end
$var reg 1 % d $end
$scope module uut $end
$var wire 1 " a $end
$var wire 1 # b $end
$var wire 1 $ c $end
$var wire 1 % d $end
$var wire 1 ! f $end
$var wire 1 & k1 $end
$var wire 1 ' k2 $end
$var wire 1 ( k3 $end
$var wire 1 ) k4 $end
$var wire 1 * k5 $end
$var wire 1 + k6 $end
$upscope $end
$upscope $end
$enddefinitions $end
$comment Show the parameter values. $end
$dumpall
$end
#0
$dumpvars
0+
0*
0)
0(
0'
0&
0%
0$
0#
0"
0!
$end
#20
1!
1*
1+
1%
#40
0!
0*
1(
1)
0%
1$
#60
1%
#80
0+
0(
0)
0%
0$
1#
#100
1!
1*
1+
1%
#120
0!
0*
1(
1)
0%
1$
#140
1%
#160
0+
0(
0)
0%
0$
0#
1"
#180
1!
1*
1+
1%
#200
0!
0*
1(
1)
0%
1$
#220
1%
#240
1&
1'
0%
0$
1#
#260
1%
#280
0%
1$
#300
1%
