Digital System Design Lab/Week 7/q3/bcdtoe3.v
module bcdtoe3(b,x);
    input [3:0] b;
    output [3:0] x;
    wire [2:0] s;
    assign s = {b[3],b[2],b[1]};

    MUX8to1 stage0({1'b0, 1'b0, b[0], 1'b1, 1'b1, {3{1'b0}}},s,x[3]);
    MUX8to1 stage1({b[0], 1'b1, ~b[0], 1'b0, b[0], {3{1'b0}}},s,x[2]);
    MUX8to1 stage2({~b[0], b[0],~b[0], b[0],~b[0], {3{1'b0}}},s,x[1]);
    MUX8to1 stage3({{5{~b[0]}}, {3{1'b0}}},s,x[0]);

endmodule


module MUX8to1(w,s,f);
    input [0:7] w;
    input [2:0] s;
    output f;
    reg f;

    always @(w or s)
    case (s)
        0: f = w[0];
        1: f = w[1];
        2: f = w[2];
        3: f = w[3];
        4: f = w[4];
        5: f = w[5];
        6: f = w[6];
        7: f = w[7];         
    endcase

endmodule

Digital System Design Lab/Week 7/q3/bcdtoe3_tb.v
`timescale 1ns/1ns
`include "bcdtoe3.v"

module bcdtoe3_tb();
reg [3:0] w;
wire [3:0] x;

bcdtoe3 q(w,x);
initial
begin 

    $dumpfile("bcdtoe3_tb.vcd");
    $dumpvars(0,bcdtoe3_tb);

    w = 4'b0000; #20;
    w = 4'b0001; #20;
    w = 4'b0010; #20;
    w = 4'b0011; #20;
    w = 4'b0100; #20;
    w = 4'b0101; #20;
    w = 4'b0110; #20;
    w = 4'b0111; #20;
    w = 4'b1000; #20;
    w = 4'b1001; #20;

    $display("Test Complete");

end
endmodule

Digital System Design Lab/Week 7/q3/bcdtoe3_tb.vcd
$date
	Mon Oct 17 10:38:59 2022
$end
$version
	Icarus Verilog
$end
$timescale
	1ns
$end
$scope module bcdtoe3_tb $end
$var wire 4 ! x [3:0] $end
$var reg 4 " w [3:0] $end
$scope module q $end
$var wire 4 # b [3:0] $end
$var wire 4 $ x [3:0] $end
$var wire 3 % s [2:0] $end
$scope module stage0 $end
$var wire 3 & s [2:0] $end
$var wire 8 ' w [0:7] $end
$var reg 1 ( f $end
$upscope $end
$scope module stage1 $end
$var wire 3 ) s [2:0] $end
$var wire 8 * w [0:7] $end
$var reg 1 + f $end
$upscope $end
$scope module stage2 $end
$var wire 3 , s [2:0] $end
$var wire 8 - w [0:7] $end
$var reg 1 . f $end
$upscope $end
$scope module stage3 $end
$var wire 3 / s [2:0] $end
$var wire 8 0 w [0:7] $end
$var reg 1 1 f $end
$upscope $end
$upscope $end
$upscope $end
$enddefinitions $end
#0
$dumpvars
11
b11111000 0
b0 /
1.
b10101000 -
b0 ,
0+
b1100000 *
b0 )
0(
b11000 '
b0 &
b0 %
b11 $
b0 #
b0 "
b11 !
$end
#20
0.
01
b100 !
b100 $
1+
b0 0
b111000 '
b11001000 *
b1010000 -
b1 "
b1 #
#40
b101 !
b101 $
11
b11111000 0
b1 %
b1 &
b1 )
b1 ,
b1 /
b11000 '
b1100000 *
b10101000 -
b10 "
b10 #
#60
01
b110 !
b110 $
1.
b0 0
b111000 '
b11001000 *
b1010000 -
b11 "
b11 #
#80
11
1+
b111 !
b111 $
1.
b11111000 0
b10 %
b10 &
b10 )
b10 ,
b10 /
b11000 '
b1100000 *
b10101000 -
b100 "
b100 #
#100
0+
0.
01
b1000 !
b1000 $
1(
b0 0
b111000 '
b11001000 *
b1010000 -
b101 "
b101 #
#120
b1001 !
b1001 $
11
b11111000 0
b11 %
b11 &
b11 )
b11 ,
b11 /
b11000 '
b1100000 *
b10101000 -
b110 "
b110 #
#140
01
b1010 !
b1010 $
1.
b0 0
b111000 '
b11001000 *
b1010000 -
b111 "
b111 #
#160
b1011 !
b1011 $
11
b11111000 0
b100 %
b100 &
b100 )
b100 ,
b100 /
b11000 '
b1100000 *
b10101000 -
b1000 "
b1000 #
#180
01
1+
b1100 !
b1100 $
0.
b0 0
b111000 '
b11001000 *
b1010000 -
b1001 "
b1001 #
