Digital System Design Lab/Week 4/Decomposed Full Adder/lab4q1c.v
module lab4q1c(a,b,Cin,s,Cout);
input a,b,Cin;
output s,Cout;
halfadd stage0(a,b,s0,c0);
halfadd stage1(s0,Cin,s,c1);
assign Cout = (c0|c1);
endmodule

module halfadd(a,b,s,Cout);
input a,b;
output s,Cout;
assign s = a^b;
assign Cout = a&b;
endmodule

Digital System Design Lab/Week 4/Decomposed Full Adder/lab4q1c_tb.v
`timescale 1ns/1ns
`include "lab4q1c.v"

module lab4q1c_tb;

reg a,b,Cin;
wire s,Cout;

lab4q1c uut(a,b,Cin,s,Cout);
initial begin

	$dumpfile("lab4q1c_tb.vcd");
	$dumpvars(0,lab4q1c_tb);
	
	a=0;
	b=0;
    Cin=0;
	#10;
	
	a=0;
	b=0;
    Cin=1;
	#10;

	a=0;
	b=1;
    Cin=0;
	#10;

	a=0;
	b=1;
    Cin=1;
	#10;

	a=1;
	b=0;
    Cin=0;
	#10;

	a=1;
	b=0;
    Cin=1;
	#10;

	a=1;
	b=1;
    Cin=0;
	#10;

	a=1;
	b=1;
    Cin=1;
	#10;

	$display("Test complete");
end
endmodule

Digital System Design Lab/Week 4/Decomposed Full Adder/lab4q1c_tb.vcd
$date
	Mon Sep 12 10:41:26 2022
$end
$version
	Icarus Verilog
$end
$timescale
	1ns
$end
$scope module lab4q1c_tb $end
$var wire 1 ! s $end
$var wire 1 " Cout $end
$var reg 1 # Cin $end
$var reg 1 $ a $end
$var reg 1 % b $end
$scope module uut $end
$var wire 1 # Cin $end
$var wire 1 " Cout $end
$var wire 1 $ a $end
$var wire 1 % b $end
$var wire 1 & s0 $end
$var wire 1 ! s $end
$var wire 1 ' c1 $end
$var wire 1 ( c0 $end
$scope module stage0 $end
$var wire 1 ( Cout $end
$var wire 1 $ a $end
$var wire 1 % b $end
$var wire 1 & s $end
$upscope $end
$scope module stage1 $end
$var wire 1 ' Cout $end
$var wire 1 & a $end
$var wire 1 # b $end
$var wire 1 ! s $end
$upscope $end
$upscope $end
$upscope $end
$enddefinitions $end
#0
$dumpvars
0(
0'
0&
0%
0$
0#
0"
0!
$end
#10
1!
1#
#20
1&
0#
1%
#30
1"
0!
1'
1#
#40
0"
1!
0'
0#
0%
1$
#50
1"
0!
1'
1#
#60
0'
0&
1(
0#
1%
#70
1!
1#
