Digital System Design Lab/Week 4/Full Adder/lab4q1b.v
// code for a 1-bit full adder
module lab4q1b(c_in, x, y, sum, c_out);
    input c_in, x, y;
    output sum, c_out;

    // calculating sum by XORing
    assign sum = c_in ^ x ^ y;

    // calculating carry out by ADDing and ORing
    assign c_out = (x & y) | (y & c_in) | (c_in & x);
endmodule

Digital System Design Lab/Week 4/Full Adder/lab4q1b_tb.v
`timescale 1ns/1ns
`include "lab4q1b.v"

module lab4q1b_tb;

reg x,y,c_in;
wire sum,c_out;

lab4q1b uut(c_in, x, y, sum, c_out);
initial begin

	$dumpfile("lab4q1b_tb.vcd");
	$dumpvars(0,lab4q1b_tb);
	
	x=0;
	y=0;
    c_in=0;
	#10;
	
	x=0;
	y=0;
    c_in=1;
	#10;

	x=0;
	y=1;
    c_in=0;
	#10;

	x=0;
	y=1;
    c_in=1;
	#10;

	x=1;
	y=0;
    c_in=0;
	#10;

	x=1;
	y=0;
    c_in=1;
	#10;

	x=1;
	y=1;
    c_in=0;
	#10;

	x=1;
	y=1;
    c_in=1;
	#10;
	
	$display("Test complete");
end
endmodule

Digital System Design Lab/Week 4/Full Adder/lab4q1b_tb.vcd
$date
	Mon Sep 12 10:36:38 2022
$end
$version
	Icarus Verilog
$end
$timescale
	1ns
$end
$scope module lab4q1b_tb $end
$var wire 1 ! sum $end
$var wire 1 " c_out $end
$var reg 1 # c_in $end
$var reg 1 $ x $end
$var reg 1 % y $end
$scope module uut $end
$var wire 1 # c_in $end
$var wire 1 " c_out $end
$var wire 1 ! sum $end
$var wire 1 $ x $end
$var wire 1 % y $end
$upscope $end
$upscope $end
$enddefinitions $end
#0
$dumpvars
0%
0$
0#
0"
0!
$end
#10
1!
1#
#20
1!
0#
1%
#30
1"
0!
1#
#40
0"
1!
0#
0%
1$
#50
0!
1"
1#
#60
0!
0#
1%
#70
1!
1#
