Digital System Design Lab/Week 2/q2_a/lab2ex2a.v
module lab2ex2a(a, b, c, d, f1,f2);
input a, b, c, d;
output f1,f2;

//Behavioural Code
assign f1 = (c|b)&(~b|d);

//Structural Code
or(k1,c,b);
or(k2,~b,d);
and(f2,k1,k2);
endmodule

Digital System Design Lab/Week 2/q2_a/lab2ex2a_input.v
`timescale 1ns/1ns
`include "lab2ex2a.v"

module lab2ex2a_input();
reg a,b,c,d;
wire f1,f2;
lab2ex2a uut(a,b,c,d,f1,f2);
initial begin

	$dumpfile("lab2ex2a_input.vcd");
	$dumpvars(0, lab2ex2a_input);
	a=0;b=0;c=0;d=0;
	#20;
	a=0;b=0;c=0;d=1;
	#20;
	a=0;b=0;c=1;d=0;
	#20;
	a=0;b=0;c=1;d=1;
	#20;
	a=0;b=1;c=0;d=0;
	#20;
	a=0;b=1;c=0;d=1;
	#20;
	a=0;b=1;c=1;d=0;
	#20;
	a=0;b=1;c=1;d=1;
	#20;
	a=1;b=0;c=0;d=0;
	#20;
	a=1;b=0;c=0;d=1;
	#20;
	a=1;b=0;c=1;d=0;
	#20;
	a=1;b=0;c=1;d=1;
	#20;
	a=1;b=1;c=0;d=0;
	#20;
	a=1;b=1;c=0;d=1;
	#20;
	a=1;b=1;c=1;d=0;
	#20;
	a=1;b=1;c=1;d=1;
	#20;
	$display("Test Complete");
end
endmodule

Digital System Design Lab/Week 2/q2_a/lab2ex2a_input.vcd
$date
	Mon Aug 29 11:15:11 2022
$end
$version
	Icarus Verilog
$end
$timescale
	1ns
$end
$scope module lab2ex2a_input $end
$var wire 1 ! f2 $end
$var wire 1 " f1 $end
$var reg 1 # a $end
$var reg 1 $ b $end
$var reg 1 % c $end
$var reg 1 & d $end
$scope module uut $end
$var wire 1 # a $end
$var wire 1 $ b $end
$var wire 1 % c $end
$var wire 1 & d $end
$var wire 1 " f1 $end
$var wire 1 ! f2 $end
$var wire 1 ' k1 $end
$var wire 1 ( k2 $end
$upscope $end
$upscope $end
$enddefinitions $end
#0
$dumpvars
1(
0'
0&
0%
0$
0#
0"
0!
$end
#20
1&
#40
1"
1!
1'
0&
1%
#60
1&
#80
0"
0!
0(
0&
0%
1$
#100
1"
1!
1(
1&
#120
0"
0!
0(
0&
1%
#140
1"
1!
1(
1&
#160
0"
0!
0'
0&
0%
0$
1#
#180
1&
#200
1"
1!
1'
0&
1%
#220
1&
#240
0"
0!
0(
0&
0%
1$
#260
1"
1!
1(
1&
#280
0"
0!
0(
0&
1%
#300
1"
1!
1(
1&
