Digital System Design Lab/Week 1/labex2.v
module labex2(a,b,c,d,f,g);
input a,b,c,d;
output f,g;
assign f=(d^~(a&b)^c);
assign g=(~(b|c|d));
endmodule

Digital System Design Lab/Week 1/Lab 1/labex2_input.v
`timescale 1ns/1ns
`include "labex2.v"

module labex2_input();
reg a,b,c,d;
wire f,g;

labex2 uut(a,b,c,d,f,g); 
initial begin

	$dumpfile("labex2_input.vcd");
	$dumpvars(0, labex2_input);

	a=0; b=0; c=0; d=0;
	#20;
	
	a=0; b=0; c=0; d=1;
	#20;
	
	a=0; b=0; c=1; d=0;
	#20;
	
	a=0; b=0; c=1; d=1;
	#20;
	
	a=0; b=1; c=0; d=0;
	#20;
	
	a=0; b=1; c=0; d=1;
	#20;
	
	a=0; b=1; c=1; d=0;
	#20;
	
	a=0; b=1; c=1; d=1;
	#20;
	
	a=1; b=0; c=0; d=0;
	#20;
	
	a=1; b=0; c=0; d=1;
	#20;
	
	a=1; b=0; c=1; d=0;
	#20;
	
	a=1; b=0; c=1; d=1;
	#20;
	
	a=1; b=1; c=0; d=0;
	#20;
	
	a=1; b=1; c=0; d=1;
	#20;
	
	a=1; b=1; c=1; d=0;
	#20;
	
	a=1; b=1; c=1; d=1;
	#20;	
	$display("Test complete");
	
end
endmodule

Digital System Design Lab/Week 1/labex2_input.vcd
$date
	Mon Aug 22 11:23:45 2022
$end
$version
	Icarus Verilog
$end
$timescale
	1ns
$end
$scope module labex2_input $end
$var wire 1 ! g $end
$var wire 1 " f $end
$var reg 1 # a $end
$var reg 1 $ b $end
$var reg 1 % c $end
$var reg 1 & d $end
$scope module uut $end
$var wire 1 # a $end
$var wire 1 $ b $end
$var wire 1 % c $end
$var wire 1 & d $end
$var wire 1 " f $end
$var wire 1 ! g $end
$upscope $end
$upscope $end
$enddefinitions $end
#0
$dumpvars
0&
0%
0$
0#
1"
1!
$end
#20
0"
0!
1&
#40
0"
0&
1%
#60
1"
1&
#80
1"
0&
0%
1$
#100
0"
1&
#120
0"
0&
1%
#140
1"
1&
#160
1!
1"
0&
0%
0$
1#
#180
0"
0!
1&
#200
0"
0&
1%
#220
1"
1&
#240
0"
0&
0%
1$
#260
1"
1&
#280
1"
0&
1%
#300
0"
1&
