Digital System Design Lab/Week 2/q1_a/lab2ex1a.v
module lab2ex1a(a,b,c,d,f1,f2);
//Behavioural Code
input a,b,c,d;
output f1,f2;
assign f1 = (~a & b) | (~b & c) | (b & ~c & ~d) | (c & d);
// Structural Code
and(k1,b,~c,~d);
and(k2,~a,b);
and(k3,c,d);
and(k4,~b,c);
or(f2,k1,k2,k3,k4);
endmodule

Digital System Design Lab/Week 2/q1_a/lab2ex1a_input.v
`timescale 1ns/1ns
`include "lab2ex1a.v"

module lab2ex1a_input();
reg a,b,c,d;
wire f1,f2;
lab2ex1a uut(a,b,c,d,f1,f2);
initial begin

	$dumpfile("lab2ex1a_input.vcd");
	$dumpvars(0, lab2ex1a_input);
	a=0;b=0;c=0;d=0;
	#20;
	a=0;b=0;c=0;d=1;
	#20;
	a=0;b=0;c=1;d=0;
	#20;
	a=0;b=0;c=1;d=1;
	#20;
	a=0;b=1;c=0;d=0;
	#20;
	a=0;b=1;c=0;d=1;
	#20;
	a=0;b=1;c=1;d=0;
	#20;
	a=0;b=1;c=1;d=1;
	#20;
	a=1;b=0;c=0;d=0;
	#20;
	a=1;b=0;c=0;d=1;
	#20;
	a=1;b=0;c=1;d=0;
	#20;
	a=1;b=0;c=1;d=1;
	#20;
	a=1;b=1;c=0;d=0;
	#20;
	a=1;b=1;c=0;d=1;
	#20;
	a=1;b=1;c=1;d=0;
	#20;
	a=1;b=1;c=1;d=1;
	#20;
	$display("Test Complete");
end
endmodule

Digital System Design Lab/Week 2/q1_a/lab2ex1a_input.vcd
$date
	Mon Aug 29 11:08:13 2022
$end
$version
	Icarus Verilog
$end
$timescale
	1ns
$end
$scope module lab2ex1a_input $end
$var wire 1 ! f2 $end
$var wire 1 " f1 $end
$var reg 1 # a $end
$var reg 1 $ b $end
$var reg 1 % c $end
$var reg 1 & d $end
$scope module uut $end
$var wire 1 # a $end
$var wire 1 $ b $end
$var wire 1 % c $end
$var wire 1 & d $end
$var wire 1 " f1 $end
$var wire 1 ! f2 $end
$var wire 1 ' k1 $end
$var wire 1 ( k2 $end
$var wire 1 ) k3 $end
$var wire 1 * k4 $end
$upscope $end
$upscope $end
$enddefinitions $end
#0
$dumpvars
0*
0)
0(
0'
0&
0%
0$
0#
0"
0!
$end
#20
1&
#40
1"
1!
1*
0&
1%
#60
1)
1&
#80
1'
0)
0*
1(
0&
0%
1$
#100
0'
1&
#120
0&
1%
#140
1)
1&
#160
0"
0!
0)
0(
0&
0%
0$
1#
#180
1&
#200
1"
1!
1*
0&
1%
#220
1)
1&
#240
1'
1!
0)
0*
0&
0%
1$
#260
0"
0!
0'
1&
#280
0&
1%
#300
1"
1!
1)
1&
